[
  {
    "id": 1,
    "image": "/assets/home/cards/michael.png",
    "hoverImage": "/assets/home/cards_position/michael.png",
    "title": "michael kors",
    "desc": "Slim Runway Gold-Tone Curb-Link Watch",
    "price": "379AZN",
    "isNew": false,
    "coupon": 20
  },
  {
    "id": 2,
    "image": "/assets/home/cards/olivia-pink.png",
    "hoverImage": "/assets/home/cards_position/olivia-pink.png",
    "title": "olivia burton",
    "desc": "Wonderland 30mm White & Rose Gold Mesh",
    "price": "200AZN",
    "isNew": true,
    "coupon": 10
  },
  {
    "id": 3,
    "image": "/assets/home/cards/hilfiger.png",
    "hoverImage": "/assets/home/cards_position/hilfiger.png",
    "title": "hilfiger",
    "desc": "32MM Monochrome Mesh Bracelet Watch",
    "price": "400AZN",
    "isNew": false,
    "coupon": 0
  },
  {
    "id": 4,
    "image": "/assets/home/cards/olivia-black.png",
    "hoverImage": "/assets/home/cards_position/olivia-black.png",
    "title": "olivia burton",
    "desc": "32mm Dimension T-Bar Gold&Black Leather Strap",
    "price": "450AZN",
    "isNew": true,
    "coupon": 0
  },
  {
    "id": 5,
    "image": "/assets/home/cards/swiss.png",
    "hoverImage": "/assets/home/cards_position/swiss.png",
    "title": "swiss military",
    "desc": "MAJESTE PIONER",
    "price": "365AZN",
    "isNew": false,
    "coupon": 20
  }
]
